README.md
setup.py
degiropy/__init__.py
degiropy/client.py
degiropy/order.py
degiropy/portfolio.py
degiropy/types.py
degiropy.egg-info/PKG-INFO
degiropy.egg-info/SOURCES.txt
degiropy.egg-info/dependency_links.txt
degiropy.egg-info/not-zip-safe
degiropy.egg-info/requires.txt
degiropy.egg-info/top_level.txt