Metadata-Version: 2.1
Name: degiropy
Version: 0.1.2
Summary: Unofficial Degiro API in python
Home-page: https://github.com/alexberazouski/degiropy
Author: Alex Berazouski
Author-email: alex.berazouski@gmail.com
License: BSD 2
Platform: UNKNOWN
Classifier: Programming Language :: Python :: 3
Classifier: License :: OSI Approved :: BSD License
Classifier: Operating System :: OS Independent
Requires-Python: >=3.6
